anyfield_auth_backend/__init__.py
anyfield_auth_backend/anyfield_auth.py
anyfield_auth_backend/apps.py
anyfield_auth_backend/tests.py
django_anyfield_auth_backend-1.0.1.dist-info/METADATA
django_anyfield_auth_backend-1.0.1.dist-info/WHEEL
django_anyfield_auth_backend-1.0.1.dist-info/top_level.txt
django_anyfield_auth_backend-1.0.1.dist-info/RECORD
