Metadata-Version: 2.1
Name: django-anyfield-auth-backend
Version: 1.0.1
Summary: Django Authentication backend that can use any field in the user table for identification.
Home-page: https://gitlab.com/rristow/django_anyfield_auth_backend
Author: Rodrigo Ristow
Author-email: rodrigo@maxttor.com
License: BSD
Keywords: django authentication
Platform: UNKNOWN
Classifier: Development Status :: 3 - Alpha
Classifier: Topic :: Utilities
Classifier: License :: OSI Approved :: BSD License
